{"symbols":{"ParsedLog":{"hasNamespace":false,"type":1,"moduleName":"Message","relativePath":"src/lib/Message"},"GitMessage":{"hasNamespace":false,"type":0,"moduleName":"Message","relativePath":"src/lib/Message"}},"files":{"src/index.ts":"2021-05-15T07:32:00.396Z","build/index.d.ts":"2021-05-15T16:09:52.806Z","build/test/tests.d.ts":"2021-05-15T01:25:46.713Z","src/test/parsing.ts":"2021-05-15T17:10:53.139Z","src/lib/Message.ts":"2021-05-15T17:19:16.991Z","build/test/parsing.d.ts":"2021-05-15T16:09:52.825Z","build/lib/Message.d.ts":"2021-05-15T16:09:52.823Z"}}